CONTRIBUTING.md
LICENCE.txt
MANIFEST.in
PYPI.md
README.md
pyproject.toml
requirements-extra.txt
requirements.txt
setup.py
bin/lava-ami
bin/lava-backup
bin/lava-check
bin/lava-checksum
bin/lava-conn-usage
bin/lava-dag-gen
bin/lava-dispatcher
bin/lava-dump
bin/lava-email
bin/lava-events
bin/lava-job-activity
bin/lava-new
bin/lava-ps
bin/lava-schema
bin/lava-sharepoint
bin/lava-slack
bin/lava-smb
bin/lava-sql
bin/lava-state
bin/lava-stop
bin/lava-version
bin/lava-worker
bin/lava-ws
bin/s3lambda
jinlava.egg-info/PKG-INFO
jinlava.egg-info/SOURCES.txt
jinlava.egg-info/dependency_links.txt
jinlava.egg-info/requires.txt
jinlava.egg-info/top_level.txt
lava/VERSION.json
lava/__init__.py
lava/actions.py
lava/common.py
lava/config.py
lava/event.py
lava/foreach.py
lava/lava.py
lava/lavacore.py
lava/version.py
lava/connection/__init__.py
lava/connection/aws.py
lava/connection/core.py
lava/connection/docker.py
lava/connection/email.py
lava/connection/generic.py
lava/connection/mssql.py
lava/connection/mysql.py
lava/connection/oracle.py
lava/connection/postgres.py
lava/connection/rds.py
lava/connection/redshift.py
lava/connection/sharepoint.py
lava/connection/slack.py
lava/connection/smb.py
lava/connection/sqlalchemy.py
lava/connection/sqlite3.py
lava/connection/ssh.py
lava/handlers/__init__.py
lava/handlers/chain.py
lava/handlers/cmd.py
lava/handlers/dag.py
lava/handlers/db_from_s3.py
lava/handlers/dispatch.py
lava/handlers/docker.py
lava/handlers/exe.py
lava/handlers/foreach.py
lava/handlers/lavasched.py
lava/handlers/log.py
lava/handlers/pkg.py
lava/handlers/redshift_unload.py
lava/handlers/sharepoint_get_doc.py
lava/handlers/sharepoint_get_list.py
lava/handlers/sharepoint_get_multi_doc.py
lava/handlers/sharepoint_put_doc.py
lava/handlers/sharepoint_put_list.py
lava/handlers/smb_get.py
lava/handlers/smb_put.py
lava/handlers/sql.py
lava/handlers/sqlc.py
lava/handlers/sqli.py
lava/handlers/sqlv.py
lava/lib/__init__.py
lava/lib/argparse.py
lava/lib/aws.py
lava/lib/daemon.py
lava/lib/dag.py
lava/lib/datetime.py
lava/lib/db.py
lava/lib/dbnone.py
lava/lib/decorators.py
lava/lib/email.py
lava/lib/fileops.py
lava/lib/jsonschema.py
