Metadata-Version: 2.1
Name: jinlava
Version: 8.2.0
Summary: AWS based distributed scheduler and job runner
Home-page: https://github.com/jin-gizmo/lava
Author: Murray Andrews, Chris Donoghue, Alex Bool
License: BSD-3-Clause
Platform: macOS
Platform: Linux
Classifier: Development Status :: 5 - Production/Stable
Classifier: Environment :: Console
Classifier: Intended Audience :: Developers
Classifier: Intended Audience :: Information Technology
Classifier: Intended Audience :: System Administrators
Classifier: Natural Language :: English
Classifier: Operating System :: MacOS
Classifier: Operating System :: POSIX :: Linux
Classifier: Programming Language :: Python :: 3 :: Only
Classifier: Topic :: Utilities
Requires-Python: >=3.11.0
Provides-Extra: extras
License-File: LICENCE.txt
